napalm/_SUPPORTED_DRIVERS.py
napalm/__init__.py
napalm/base/__init__.py
napalm/base/base.py
napalm/base/canonical_map.py
napalm/base/constants.py
napalm/base/exceptions.py
napalm/base/helpers.py
napalm/base/mock.py
napalm/base/netmiko_helpers.py
napalm/base/validate.py
napalm/base/clitools/__init__.py
napalm/base/clitools/cl_napalm.py
napalm/base/clitools/cl_napalm_configure.py
napalm/base/clitools/cl_napalm_test.py
napalm/base/clitools/cl_napalm_validate.py
napalm/base/clitools/helpers.py
napalm/base/test/__init__.py
napalm/base/test/base.py
napalm/base/test/conftest.py
napalm/base/test/double.py
napalm/base/test/getters.py
napalm/base/test/helpers.py
napalm/base/test/models.py
napalm/base/utils/__init__.py
napalm/base/utils/jinja_filters.py
napalm/base/utils/string_parsers.py
napalm/eos/__init__.py
napalm/eos/constants.py
napalm/eos/eos.py
napalm/eos/pyeapi_syntax_wrapper.py
napalm/eos/templates/delete_ntp_servers.j2
napalm/eos/templates/delete_snmp_config.j2
napalm/eos/templates/delete_users.j2
napalm/eos/templates/set_ntp_servers.j2
napalm/eos/templates/set_users.j2
napalm/eos/templates/snmp_config.j2
napalm/eos/utils/__init__.py
napalm/eos/utils/cli_syntax.py
napalm/eos/utils/versions.py
napalm/eos/utils/textfsm_templates/bgp_detail.tpl
napalm/eos/utils/textfsm_templates/ntp_peers.tpl
napalm/eos/utils/textfsm_templates/snmp_config.tpl
napalm/eos/utils/textfsm_templates/vrf.tpl
napalm/ios/__init__.py
napalm/ios/ios.py
napalm/ios/templates/delete_ntp_peers.j2
napalm/ios/templates/delete_ntp_servers.j2
napalm/ios/templates/delete_snmp_config.j2
napalm/ios/templates/set_hostname.j2
napalm/ios/templates/set_ntp_peers.j2
napalm/ios/templates/set_ntp_servers.j2
napalm/ios/templates/snmp_config.j2
napalm/ios/utils/textfsm_templates/ip_bgp_all_sum.tpl
napalm/ios/utils/textfsm_templates/ip_bgp_neigh.tpl
napalm/ios/utils/textfsm_templates/ip_bgp_neigh_afi.tpl
napalm/ios/utils/textfsm_templates/show_lldp_neighbors.tpl
napalm_fork-3.4.0.post3.dist-info/LICENSE
napalm_fork-3.4.0.post3.dist-info/METADATA
napalm_fork-3.4.0.post3.dist-info/WHEEL
napalm_fork-3.4.0.post3.dist-info/entry_points.txt
napalm_fork-3.4.0.post3.dist-info/top_level.txt
napalm_fork-3.4.0.post3.dist-info/RECORD
