Metadata-Version: 2.1
Name: napalm-fork
Version: 3.4.0.post3
Summary: Network Automation and Programmability Abstraction Layer with Multivendor support
Home-page: https://github.com/napalm-automation/napalm
Author: David Barroso, Kirk Byers, Mircea Ulinic
Author-email: dbarrosop@dravetech.com, ping@mirceaulinic.net, ktbyers@twb-tech.com
License: Apache 2.0
Platform: UNKNOWN
Classifier: Topic :: Utilities
Classifier: License :: OSI Approved :: Apache Software License
Classifier: Programming Language :: Python
Classifier: Programming Language :: Python :: 3
Classifier: Programming Language :: Python :: 3.6
Classifier: Programming Language :: Python :: 3.7
Classifier: Programming Language :: Python :: 3.8
Classifier: Operating System :: POSIX :: Linux
Classifier: Operating System :: MacOS
License-File: LICENSE
Requires-Dist: setuptools (>=38.4.0)
Requires-Dist: cffi (>=1.11.3)
Requires-Dist: paramiko (>=2.6.0)
Requires-Dist: requests (>=2.7.0)
Requires-Dist: future
Requires-Dist: textfsm
Requires-Dist: jinja2
Requires-Dist: netaddr
Requires-Dist: pyYAML
Requires-Dist: pyeapi-fork (==0.8.4rc3)
Requires-Dist: netmiko (<4.0.0,>=3.3.0)
Requires-Dist: junos-eznc (>=2.2.1)
Requires-Dist: scp
Requires-Dist: lxml (>=4.3.0)
Requires-Dist: ncclient
Requires-Dist: ttp
Requires-Dist: ttp-templates
Requires-Dist: netutils (>=1.0.0)
